incendium/__about__.py
incendium/__init__.py
incendium/constants.py
incendium/dataset.py
incendium/date.py
incendium/db.py
incendium/exceptions.py
incendium/gui.py
incendium/net.py
incendium/tag.py
incendium/time.py
incendium/helper/__init__.py
incendium/helper/types.py
incendium/vision/__init__.py
incendium/vision/gui.py
incendium/vision/nav.py
incendium/vision/user.py
incendium-2025.12.0.dist-info/METADATA
incendium-2025.12.0.dist-info/WHEEL
incendium-2025.12.0.dist-info/top_level.txt
incendium-2025.12.0.dist-info/RECORD
