Metadata-Version: 2.1
Name: incendium
Version: 2025.12.0
Summary: Package that extends and wraps Ignition Scripting API
Home-page: https://github.com/ignition-devs/incendium
Author: César Román
Author-email: cesar@coatl.dev
License: MIT
Project-URL: Source, https://github.com/ignition-devs/incendium
Project-URL: Documentation, https://github.com/ignition-devs/incendium/wiki
Project-URL: Funding, https://github.com/sponsors/cesarcoatl
Project-URL: Tracker, https://github.com/ignition-devs/incendium/issues
Keywords: coatl-dev,hmi,ignition,inductive automation,scada
Platform: UNKNOWN
Classifier: Development Status :: 5 - Production/Stable
Classifier: Intended Audience :: Developers
Classifier: Intended Audience :: Information Technology
Classifier: Intended Audience :: Manufacturing
Classifier: License :: OSI Approved :: MIT License
Classifier: Operating System :: MacOS :: MacOS X
Classifier: Operating System :: Microsoft :: Windows
Classifier: Operating System :: POSIX :: Linux
Classifier: Programming Language :: Python
Classifier: Programming Language :: Python :: 2 :: Only
Classifier: Programming Language :: Python :: 2.7
Classifier: Programming Language :: Python :: Implementation :: Jython
Classifier: Topic :: Software Development :: Libraries :: Python Modules
Requires-Python: >=2.7, <3
Requires-Dist: ignition-api (>=8.3.0) ; platform_python_implementation != "Jython"
Requires-Dist: typing ; platform_python_implementation == "Jython"
